imha/__init__.py
imha/py.typed
imha-0.2.0.dist-info/licenses/LICENSE
imha-0.2.0.dist-info/WHEEL
imha-0.2.0.dist-info/entry_points.txt
imha-0.2.0.dist-info/METADATA
imha-0.2.0.dist-info/RECORD
