Metadata-Version: 2.4
Name: imha
Version: 0.2.0
Summary: A more constrained and friendlier fork of ImageHash.
Keywords: average hash,dhash,image hash,image hashing,imagehash
Author: Eric Nielsen
License-Expression: BSD-2-Clause
License-File: LICENSE
Classifier: Development Status :: 5 - Production/Stable
Classifier: Topic :: Scientific/Engineering :: Image Processing
Classifier: Programming Language :: Python :: 3
Classifier: Programming Language :: Python :: 3.10
Classifier: Programming Language :: Python :: 3.11
Classifier: Programming Language :: Python :: 3.12
Classifier: Programming Language :: Python :: 3.13
Classifier: Programming Language :: Python :: 3.14
Requires-Dist: pillow>=9.1.0
Requires-Python: >=3.10
Project-URL: Changelog, https://github.com/ericbn/imha/blob/master/CHANGELOG.md
Project-URL: Issues, https://github.com/ericbn/imha/issues
Project-URL: Repository, https://github.com/ericbn/imha.git
